cellbin/__init__.py
cellbin/contrib/GMM_correct.py
cellbin/contrib/__init__.py
cellbin/contrib/alignment.py
cellbin/contrib/alignment2he.py
cellbin/contrib/cell_mask.py
cellbin/contrib/fast_correct.py
cellbin/contrib/fov_aligner.py
cellbin/contrib/global_location.py
cellbin/contrib/line_detector.py
cellbin/contrib/roi_track.py
cellbin/contrib/template_match.py
cellbin/contrib/template_reference.py
cellbin/contrib/template_reference_v2.py
cellbin/contrib/track_roi_picker.py
cellbin/contrib/vision_track.py
cellbin/dnn/__init__.py
cellbin/dnn/common.py
cellbin/dnn/onnx_net.py
cellbin/dnn/tensorrt_net.py
cellbin/dnn/clarity/__init__.py
cellbin/dnn/clarity/evaler.py
cellbin/dnn/cseg/__init__.py
cellbin/dnn/cseg/cell_trace.py
cellbin/dnn/cseg/detector.py
cellbin/dnn/cseg/predict.py
cellbin/dnn/cseg/processing.py
cellbin/dnn/pdetect/__init__.py
cellbin/dnn/pdetect/pt_detector.py
cellbin/dnn/pdetect/util.py
cellbin/dnn/tseg/__init__.py
cellbin/dnn/tseg/bcdu/__init__.py
cellbin/dnn/tseg/bcdu/detector.py
cellbin/dnn/tseg/bcdu/processing.py
cellbin/dnn/tseg/yolo/__init__.py
cellbin/dnn/tseg/yolo/detector.py
cellbin/dnn/tseg/yolo/nms.py
cellbin/dnn/tseg/yolo/processing.py
cellbin/dnn/weights/__init__.py
cellbin/image/__init__.py
cellbin/image/augmentation.py
cellbin/image/mask.py
cellbin/image/morphology.py
cellbin/image/threshold.py
cellbin/image/transform.py
cellbin/image/wsi_split.py
cellbin/image/wsi_stitch.py
cellbin/modules/__init__.py
cellbin/modules/calibrate.py
cellbin/modules/cell_labelling.py
cellbin/modules/cell_segmentation.py
cellbin/modules/image_qc.py
cellbin/modules/registration.py
cellbin/modules/stitching.py
cellbin/modules/tissue_segmentation.py
cellbin/modules/iqc/__init__.py
cellbin/modules/iqc/clarity_qc.py
cellbin/modules/iqc/classify_fov.py
cellbin/modules/iqc/regist_qc.py
cellbin/modules/iqc/stitch_qc.py
cellbin/modules/iqc/track_line.py
cellbin/modules/iqc/track_pt.py
cellbin/modules/mif_calibrate/__init__.py
cell_bin-1.3.4.1.dist-info/METADATA
cell_bin-1.3.4.1.dist-info/WHEEL
cell_bin-1.3.4.1.dist-info/top_level.txt
cell_bin-1.3.4.1.dist-info/RECORD
