Metadata-Version: 2.1
Name: cell-bin
Version: 1.3.4.1
Summary: A framework for generating single-cell gene expression data
Home-page: https://gitlab.genomics.cn/biointelligence/implab/stero-rnd/cellbin/algorithms/cellbin/-/tree/dev
Author: cell bin research group
Author-email: bgi@genomics.cn
Classifier: Development Status :: 3 - Alpha
Classifier: Intended Audience :: Developers
Classifier: License :: OSI Approved :: MIT License
Requires-Python: ==3.8.*
Requires-Dist: numpy (==1.23.5)
Requires-Dist: tifffile (==2023.2.3)
Requires-Dist: scikit-image (==0.21.0)
Requires-Dist: opencv-python (==4.8.0.76)
Requires-Dist: onnxruntime (==1.15.1)
Requires-Dist: tqdm (==4.65.0)
Requires-Dist: scikit-learn (==1.3.0)
Requires-Dist: imagecodecs (==2023.3.16)
Requires-Dist: pandas (==1.5.3)
Requires-Dist: pyvips (==2.2.1)
Requires-Dist: requests
Requires-Dist: matplotlib (==3.7.1)
Requires-Dist: h5py (==3.8.0)
